xgit/__init__.py
xgit/cmds/__init__.py
xgit/cmds/modify.py
xgit/cmds/summary.py
xgit/cmds/tag.py
xgit/cmds/update.py
xgit/utils/__init__.py
xgit/utils/git/__init__.py
xgit/utils/git/config.py
xgit/utils/git/execute.py
xgit/utils/git/reference.py
xgit_python-0.6.dist-info/LICENSE
xgit_python-0.6.dist-info/METADATA
xgit_python-0.6.dist-info/WHEEL
xgit_python-0.6.dist-info/entry_points.txt
xgit_python-0.6.dist-info/top_level.txt
xgit_python-0.6.dist-info/zip-safe
xgit_python-0.6.dist-info/RECORD
