Metadata-Version: 2.1
Name: xgit-python
Version: 0.6
Summary: Git tool based on GitPython.
Home-page: https://github.com/bondbox/xgit-python
Author: Mingzhe Zou
Author-email: zoumingzhe@outlook.com
License: MIT
Project-URL: Source Code, https://github.com/bondbox/xgit-python
Project-URL: Bug Tracker, https://github.com/bondbox/xgit-python/issues
Project-URL: Documentation, https://github.com/bondbox/xgit-python
Keywords: git,GitPython,xgit
Platform: any
Classifier: Programming Language :: Python
Classifier: Programming Language :: Python :: 3
Requires-Python: >=3.8
License-File: LICENSE
Requires-Dist: GitPython
Requires-Dist: tabulate
Requires-Dist: xarg-python (>=1.1)
